Metadata-Version: 2.1
Name: yowasp-nextpnr-ecp5-25k
Version: 9999
Summary: nextpnr-ecp5 FPGA place and route tool
Author: whitequark
Author-email: whitequark@whitequark.org
License: ISC
Project-URL: Homepage, https://yowasp.github.io/
Project-URL: Source Code, https://github.com/YoWASP/nextpnr
Project-URL: Bug Tracker, https://github.com/YoWASP/nextpnr/issues
Classifier: License :: OSI Approved :: ISC License (ISCL)
Requires-Python: ~=3.5
Requires-Dist: USE-yowasp-nextpnr-ecp5-INSTEAD
